aiodeta/__init__.py
aiodeta/client.py
aiodeta-0.1.2.dist-info/LICENSE
aiodeta-0.1.2.dist-info/WHEEL
aiodeta-0.1.2.dist-info/METADATA
aiodeta-0.1.2.dist-info/RECORD
