Metadata-Version: 2.1
Name: aiodeta
Version: 0.1.2
Summary: Unofficial Deta client
Home-page: https://github.com/leits/aiodeta
License: MIT
Author: leits
Author-email: leits.dev@gmail.com
Requires-Python: >=3.7,<4.0
Classifier: License :: OSI Approved :: MIT License
Classifier: Programming Language :: Python :: 3
Classifier: Programming Language :: Python :: 3.7
Classifier: Programming Language :: Python :: 3.8
Classifier: Programming Language :: Python :: 3.9
Requires-Dist: aiohttp (>=3.7.4,<4.0.0)
Project-URL: Repository, https://github.com/leits/aiodeta
